{
  "title": "Games",
  "path": "_games",
  "page": 16,
  "value": [
    {
      "path": "_games/lowkotv-starcraft-2-tactical-nuke-distractions-astrea-vs-dream.md",
      "title": "StarCraft 2: TACTICAL NUKE DISTRACTIONS! (Astrea vs Dream)",
      "excerpt": "Awesome game of professional StarCraft 2 between Astrea and Dream. Astrea has been making a name for himself recently as he has been taking games off of some of the best players in the world. In this match he is going up against Dream, one of the highest ranked Terran players from South Korea. Dream",
      "sourceUrl": "https://smartableai.github.io/starcraft2/api/games/lowkotv-starcraft-2-tactical-nuke-distractions-astrea-vs-dream/index.json",
      "webUrl": "https://smartable.ai/apps/starcraft2/game/lowkotv-starcraft-2-tactical-nuke-distractions-astrea-vs-dream/",
      "originalUrl": "https://youtube.com/watch?v=TBDHCJNQ2Aw",
      "featuredContent": "<iframe width=\"800\" height=\"500\" frameborder=\"0\" src=\"https://www.youtube.com/embed/TBDHCJNQ2Aw\" allow=\"accelerometer; autoplay; encrypted-media; gyroscope; picture-in-picture\" allowfullscreen></iframe>",
      "length": "PT30M24S",
      "provider": {
        "name": "LowkoTV",
        "domain": "lowko.tv",
        "images": [
          {
            "url": "https://smartableai.github.io/starcraft2/assets/images/organizations/lowko.tv-50x50.jpg",
            "width": 50,
            "height": 50,
            "isCached": false
          }
        ]
      },
      "topics": [
        "StarCraft 2",
        "Terran"
      ],
      "heat": 51,
      "images": [
        {
          "url": "https://i.ytimg.com/vi/TBDHCJNQ2Aw/maxresdefault.jpg",
          "width": 1280,
          "height": 720,
          "isCached": true
        }
      ],
      "content": "\r\n",
      "type": "video",
      "publishedDateTime": "2020-09-08T03:14:44-07:00"
    },
    {
      "path": "_games/lowkotv-starcraft-2-tactical-nuke-vs-mass-tempest.md",
      "title": "StarCraft 2: TACTICAL NUKE vs MASS TEMPEST!",
      "excerpt": "A  long macro game between TY and PartinG in StarCraft 2. Subscribe for more videos: http://lowko.tv/youtube More StarCraft 2: https://www.youtube.com/watch?v=gUE1eInkbVk  Such an awesome game of Protoss vs Terran. In this match, PartinG decides to base his unit composition around the Tempest with the",
      "sourceUrl": "https://smartableai.github.io/starcraft2/api/games/lowkotv-starcraft-2-tactical-nuke-vs-mass-tempest/index.json",
      "webUrl": "https://smartable.ai/apps/starcraft2/game/lowkotv-starcraft-2-tactical-nuke-vs-mass-tempest/",
      "originalUrl": "https://youtube.com/watch?v=X93qKtLObZQ",
      "featuredContent": "<iframe width=\"800\" height=\"500\" frameborder=\"0\" src=\"https://www.youtube.com/embed/X93qKtLObZQ\" allow=\"accelerometer; autoplay; encrypted-media; gyroscope; picture-in-picture\" allowfullscreen></iframe>",
      "length": "PT28M4S",
      "provider": {
        "name": "LowkoTV",
        "domain": "lowko.tv",
        "images": [
          {
            "url": "https://smartableai.github.io/starcraft2/assets/images/organizations/lowko.tv-50x50.jpg",
            "width": 50,
            "height": 50,
            "isCached": false
          }
        ]
      },
      "topics": [
        "StarCraft 2",
        "Terran"
      ],
      "heat": 51,
      "images": [
        {
          "url": "https://i.ytimg.com/vi/X93qKtLObZQ/maxresdefault.jpg",
          "width": 1280,
          "height": 720,
          "isCached": true
        }
      ],
      "content": "\r\n",
      "type": "video",
      "publishedDateTime": "2019-01-12T05:04:47-08:00"
    },
    {
      "path": "_games/lowkotv-starcraft-2-terran-bio-vs-terran-mech.md",
      "title": "StarCraft 2: Terran Bio vs Terran Mech!",
      "excerpt": "Terran vs Terran match of professional StarCraft 2 between Cure and Dream.  Get more videos & support my work: http://www.patreon.com/lowkotv  My second channel: http://lowko.tv/morelowko Lowko Merch: http://lowko.tv/merch  Be part of the community on Discord: http://discord.gg/lowkotv The hardware setup",
      "sourceUrl": "https://smartableai.github.io/starcraft2/api/games/lowkotv-starcraft-2-terran-bio-vs-terran-mech/index.json",
      "webUrl": "https://smartable.ai/apps/starcraft2/game/lowkotv-starcraft-2-terran-bio-vs-terran-mech/",
      "originalUrl": "https://youtube.com/watch?v=mc-3WHF1zT8",
      "featuredContent": "<iframe width=\"800\" height=\"500\" frameborder=\"0\" src=\"https://www.youtube.com/embed/mc-3WHF1zT8\" allow=\"accelerometer; autoplay; encrypted-media; gyroscope; picture-in-picture\" allowfullscreen></iframe>",
      "length": "PT17M",
      "provider": {
        "name": "LowkoTV",
        "domain": "lowko.tv",
        "images": [
          {
            "url": "https://smartableai.github.io/starcraft2/assets/images/organizations/lowko.tv-50x50.jpg",
            "width": 50,
            "height": 50,
            "isCached": false
          }
        ]
      },
      "topics": [
        "StarCraft 2",
        "Terran"
      ],
      "heat": 51,
      "images": [
        {
          "url": "https://i.ytimg.com/vi/mc-3WHF1zT8/maxresdefault.jpg",
          "width": 1280,
          "height": 720,
          "isCached": true
        }
      ],
      "content": "\r\n",
      "type": "video",
      "publishedDateTime": "2019-11-13T01:56:20-08:00"
    },
    {
      "path": "_games/lowkotv-starcraft-2-the-battlecruiser-base-race.md",
      "title": "StarCraft 2: The Battlecruiser Base Race!",
      "excerpt": "An epic game of professional Zerg vs Terran in StarCraft 2 between uThermal and Bly.   Starcraft 2 balance update: https://youtu.be/_JMCTJC2CpM  Get more videos & support my work: http://www.patreon.com/lowkotv  My second channel: http://lowko.tv/morelowko Lowko Merch: http://lowko.tv/merch  Be part",
      "sourceUrl": "https://smartableai.github.io/starcraft2/api/games/lowkotv-starcraft-2-the-battlecruiser-base-race/index.json",
      "webUrl": "https://smartable.ai/apps/starcraft2/game/lowkotv-starcraft-2-the-battlecruiser-base-race/",
      "originalUrl": "https://youtube.com/watch?v=A1-4-eltzsQ",
      "featuredContent": "<iframe width=\"800\" height=\"500\" frameborder=\"0\" src=\"https://www.youtube.com/embed/A1-4-eltzsQ\" allow=\"accelerometer; autoplay; encrypted-media; gyroscope; picture-in-picture\" allowfullscreen></iframe>",
      "length": "PT38M28S",
      "provider": {
        "name": "LowkoTV",
        "domain": "lowko.tv",
        "images": [
          {
            "url": "https://smartableai.github.io/starcraft2/assets/images/organizations/lowko.tv-50x50.jpg",
            "width": 50,
            "height": 50,
            "isCached": false
          }
        ]
      },
      "topics": [
        "StarCraft 2",
        "Terran"
      ],
      "heat": 51,
      "images": [
        {
          "url": "https://i.ytimg.com/vi/A1-4-eltzsQ/maxresdefault.jpg",
          "width": 1280,
          "height": 720,
          "isCached": true
        }
      ],
      "content": "\r\n",
      "type": "video",
      "publishedDateTime": "2019-11-13T01:56:27-08:00"
    },
    {
      "path": "_games/lowkotv-starcraft-2-the-battlecruiser-fleet.md",
      "title": "StarCraft 2: The Battlecruiser Fleet!",
      "excerpt": "An awesome game of Zerg vs Terran in StarCraft 2 between Reynor and Kelazhur.  Get more videos & support my work: http://www.patreon.com/lowkotv  My second channel: http://lowko.tv/morelowko Lowko Merch: http://lowko.tv/merch  Be part of the community on Discord: http://discord.gg/lowkotv The hardware",
      "sourceUrl": "https://smartableai.github.io/starcraft2/api/games/lowkotv-starcraft-2-the-battlecruiser-fleet/index.json",
      "webUrl": "https://smartable.ai/apps/starcraft2/game/lowkotv-starcraft-2-the-battlecruiser-fleet/",
      "originalUrl": "https://youtube.com/watch?v=wx3AgOTBp-Q",
      "featuredContent": "<iframe width=\"800\" height=\"500\" frameborder=\"0\" src=\"https://www.youtube.com/embed/wx3AgOTBp-Q\" allow=\"accelerometer; autoplay; encrypted-media; gyroscope; picture-in-picture\" allowfullscreen></iframe>",
      "length": "PT24M33S",
      "provider": {
        "name": "LowkoTV",
        "domain": "lowko.tv",
        "images": [
          {
            "url": "https://smartableai.github.io/starcraft2/assets/images/organizations/lowko.tv-50x50.jpg",
            "width": 50,
            "height": 50,
            "isCached": false
          }
        ]
      },
      "topics": [
        "StarCraft 2",
        "Terran"
      ],
      "heat": 51,
      "images": [
        {
          "url": "https://i.ytimg.com/vi/wx3AgOTBp-Q/maxresdefault.jpg",
          "width": 1280,
          "height": 720,
          "isCached": true
        }
      ],
      "content": "\r\n",
      "type": "video",
      "publishedDateTime": "2019-11-13T01:57:13-08:00"
    },
    {
      "path": "_games/lowkotv-starcraft-2-the-best-mirror-matchup-heromarine-vs-soul.md",
      "title": "StarCraft 2: THE BEST MIRROR MATCHUP! (HeroMarine vs souL)",
      "excerpt": "Terran versus Terran is an awesome matchup in StarCraft 2. In my opinion it's by far the best mirror matchup in the game. In this professional match between HeroMarine and souL both players focus their unit composition around Marines, Siege Tanks, Vikings, Medivacs and Liberators. Despite that, the dynamic",
      "sourceUrl": "https://smartableai.github.io/starcraft2/api/games/lowkotv-starcraft-2-the-best-mirror-matchup-heromarine-vs-soul/index.json",
      "webUrl": "https://smartable.ai/apps/starcraft2/game/lowkotv-starcraft-2-the-best-mirror-matchup-heromarine-vs-soul/",
      "originalUrl": "https://youtube.com/watch?v=fo65-p6vBqs",
      "featuredContent": "<iframe width=\"800\" height=\"500\" frameborder=\"0\" src=\"https://www.youtube.com/embed/fo65-p6vBqs\" allow=\"accelerometer; autoplay; encrypted-media; gyroscope; picture-in-picture\" allowfullscreen></iframe>",
      "length": "PT24M16S",
      "provider": {
        "name": "LowkoTV",
        "domain": "lowko.tv",
        "images": [
          {
            "url": "https://smartableai.github.io/starcraft2/assets/images/organizations/lowko.tv-50x50.jpg",
            "width": 50,
            "height": 50,
            "isCached": false
          }
        ]
      },
      "topics": [
        "StarCraft 2"
      ],
      "heat": 51,
      "images": [
        {
          "url": "https://i.ytimg.com/vi/fo65-p6vBqs/maxresdefault.jpg",
          "width": 1280,
          "height": 720,
          "isCached": true
        }
      ],
      "content": "\r\n",
      "type": "video",
      "publishedDateTime": "2020-07-11T03:26:33-07:00"
    },
    {
      "path": "_games/lowkotv-starcraft-2-the-blind-terran-army.md",
      "title": "StarCraft 2: The BLIND Terran Army!",
      "excerpt": "All those Terran units need to be fired. Or glasses. One of the two. Subscribe for more videos: http://lowko.tv/youtube Intense micro battles: https://goo.gl/8ofWqN  In this Protoss versus Terran we get quickly into a base trade scenario. The Terran player tries to close out the game as quickly as he",
      "sourceUrl": "https://smartableai.github.io/starcraft2/api/games/lowkotv-starcraft-2-the-blind-terran-army/index.json",
      "webUrl": "https://smartable.ai/apps/starcraft2/game/lowkotv-starcraft-2-the-blind-terran-army/",
      "originalUrl": "https://youtube.com/watch?v=BrERaMwC5fw",
      "featuredContent": "<iframe width=\"800\" height=\"500\" frameborder=\"0\" src=\"https://www.youtube.com/embed/BrERaMwC5fw\" allow=\"accelerometer; autoplay; encrypted-media; gyroscope; picture-in-picture\" allowfullscreen></iframe>",
      "length": "PT15M35S",
      "provider": {
        "name": "LowkoTV",
        "domain": "lowko.tv",
        "images": [
          {
            "url": "https://smartableai.github.io/starcraft2/assets/images/organizations/lowko.tv-50x50.jpg",
            "width": 50,
            "height": 50,
            "isCached": false
          }
        ]
      },
      "topics": [
        "StarCraft 2",
        "Terran"
      ],
      "heat": 51,
      "images": [
        {
          "url": "https://i.ytimg.com/vi/BrERaMwC5fw/maxresdefault.jpg",
          "width": 1280,
          "height": 720,
          "isCached": true
        }
      ],
      "content": "\r\n",
      "type": "video",
      "publishedDateTime": "2017-07-18T13:23:49-07:00"
    },
    {
      "path": "_games/lowkotv-starcraft-2-the-creativity-wars.md",
      "title": "StarCraft 2: The Creativity Wars!",
      "excerpt": "Has vs TLO. The two most creative players in StarCraft 2. This is a best-of-3 series that was recently played as part of the World Championship Series Fall.  Get more videos & support my work: http://www.patreon.com/lowkotv  Be part of the community on Discord: http://discord.gg/lowkotv The hardware",
      "sourceUrl": "https://smartableai.github.io/starcraft2/api/games/lowkotv-starcraft-2-the-creativity-wars/index.json",
      "webUrl": "https://smartable.ai/apps/starcraft2/game/lowkotv-starcraft-2-the-creativity-wars/",
      "originalUrl": "https://youtube.com/watch?v=jcFEZYFg0tk",
      "featuredContent": "<iframe width=\"800\" height=\"500\" frameborder=\"0\" src=\"https://www.youtube.com/embed/jcFEZYFg0tk\" allow=\"accelerometer; autoplay; encrypted-media; gyroscope; picture-in-picture\" allowfullscreen></iframe>",
      "length": "PT29M24S",
      "provider": {
        "name": "LowkoTV",
        "domain": "lowko.tv",
        "images": [
          {
            "url": "https://smartableai.github.io/starcraft2/assets/images/organizations/lowko.tv-50x50.jpg",
            "width": 50,
            "height": 50,
            "isCached": false
          }
        ]
      },
      "topics": [
        "StarCraft 2"
      ],
      "heat": 51,
      "images": [
        {
          "url": "https://i.ytimg.com/vi/jcFEZYFg0tk/maxresdefault.jpg",
          "width": 1280,
          "height": 720,
          "isCached": true
        }
      ],
      "content": "\r\n",
      "type": "video",
      "publishedDateTime": "2019-09-09T03:10:58-07:00"
    },
    {
      "path": "_games/lowkotv-starcraft-2-the-cringe-nukes.md",
      "title": "StarCraft 2: The Cringe NUKES!",
      "excerpt": "A very strange Terran vs Terran. Subscribe for more videos: http://lowko.tv/youtube Zerg vs Protoss misdirection: https://goo.gl/ByS50z  In this Gold vs Platinum League Terran vs Terran the player in Blue decides to play a bit of a strange style with Tactical Nukes and bad manner Mules.  Support me on",
      "sourceUrl": "https://smartableai.github.io/starcraft2/api/games/lowkotv-starcraft-2-the-cringe-nukes/index.json",
      "webUrl": "https://smartable.ai/apps/starcraft2/game/lowkotv-starcraft-2-the-cringe-nukes/",
      "originalUrl": "https://youtube.com/watch?v=ykgEMS8zuzI",
      "featuredContent": "<iframe width=\"800\" height=\"500\" frameborder=\"0\" src=\"https://www.youtube.com/embed/ykgEMS8zuzI\" allow=\"accelerometer; autoplay; encrypted-media; gyroscope; picture-in-picture\" allowfullscreen></iframe>",
      "length": "PT13M6S",
      "provider": {
        "name": "LowkoTV",
        "domain": "lowko.tv",
        "images": [
          {
            "url": "https://smartableai.github.io/starcraft2/assets/images/organizations/lowko.tv-50x50.jpg",
            "width": 50,
            "height": 50,
            "isCached": false
          }
        ]
      },
      "topics": [
        "StarCraft 2",
        "Terran"
      ],
      "heat": 51,
      "images": [
        {
          "url": "https://i.ytimg.com/vi/ykgEMS8zuzI/maxresdefault.jpg",
          "width": 1280,
          "height": 720,
          "isCached": true
        }
      ],
      "content": "\r\n",
      "type": "video",
      "publishedDateTime": "2017-04-29T11:57:16-07:00"
    },
    {
      "path": "_games/lowkotv-starcraft-2-the-epic-late-game.md",
      "title": "StarCraft 2: The Epic Late Game!",
      "excerpt": "An epic match of professional StarCraft 2 between Bly and Harstem. This is not a series of games, but just a single match that's extremely long. Nearly all Minerals of Triton get completely mined out in the ultimate late game of this Zerg vs Protoss.  Get more videos & support my work: http://www.patreon.com/lowkotv",
      "sourceUrl": "https://smartableai.github.io/starcraft2/api/games/lowkotv-starcraft-2-the-epic-late-game/index.json",
      "webUrl": "https://smartable.ai/apps/starcraft2/game/lowkotv-starcraft-2-the-epic-late-game/",
      "originalUrl": "https://youtube.com/watch?v=3Xyfl8EKj2I",
      "featuredContent": "<iframe width=\"800\" height=\"500\" frameborder=\"0\" src=\"https://www.youtube.com/embed/3Xyfl8EKj2I\" allow=\"accelerometer; autoplay; encrypted-media; gyroscope; picture-in-picture\" allowfullscreen></iframe>",
      "length": "PT57M47S",
      "provider": {
        "name": "LowkoTV",
        "domain": "lowko.tv",
        "images": [
          {
            "url": "https://smartableai.github.io/starcraft2/assets/images/organizations/lowko.tv-50x50.jpg",
            "width": 50,
            "height": 50,
            "isCached": false
          }
        ]
      },
      "topics": [
        "StarCraft 2"
      ],
      "heat": 51,
      "images": [
        {
          "url": "https://i.ytimg.com/vi/3Xyfl8EKj2I/maxresdefault.jpg",
          "width": 1280,
          "height": 720,
          "isCached": true
        }
      ],
      "content": "\r\n",
      "type": "video",
      "publishedDateTime": "2019-09-23T14:04:03-07:00"
    },
    {
      "path": "_games/lowkotv-starcraft-2-the-extreme-late-game.md",
      "title": "StarCraft 2: THE EXTREME LATE GAME!",
      "excerpt": "The supreme late game in an epic Zerg vs Protoss. Subscribe for more videos: http://lowko.tv/youtube More StarCraft 2 casts: https://goo.gl/bpDV8i  My first commentated match of StarCraft 2 in 2019 and it's a good one! This game almost mines out Para Site LE, a massive map in StarCraft 2. It's a game",
      "sourceUrl": "https://smartableai.github.io/starcraft2/api/games/lowkotv-starcraft-2-the-extreme-late-game/index.json",
      "webUrl": "https://smartable.ai/apps/starcraft2/game/lowkotv-starcraft-2-the-extreme-late-game/",
      "originalUrl": "https://youtube.com/watch?v=dm4j7u-Ogxg",
      "featuredContent": "<iframe width=\"800\" height=\"500\" frameborder=\"0\" src=\"https://www.youtube.com/embed/dm4j7u-Ogxg\" allow=\"accelerometer; autoplay; encrypted-media; gyroscope; picture-in-picture\" allowfullscreen></iframe>",
      "length": "PT47M45S",
      "provider": {
        "name": "LowkoTV",
        "domain": "lowko.tv",
        "images": [
          {
            "url": "https://smartableai.github.io/starcraft2/assets/images/organizations/lowko.tv-50x50.jpg",
            "width": 50,
            "height": 50,
            "isCached": false
          }
        ]
      },
      "topics": [
        "StarCraft 2"
      ],
      "heat": 51,
      "images": [
        {
          "url": "https://i.ytimg.com/vi/dm4j7u-Ogxg/maxresdefault.jpg",
          "width": 1280,
          "height": 720,
          "isCached": true
        }
      ],
      "content": "\r\n",
      "type": "video",
      "publishedDateTime": "2019-01-03T03:58:46-08:00"
    },
    {
      "path": "_games/lowkotv-starcraft-2-the-greedy-terran.md",
      "title": "StarCraft 2: THE GREEDY TERRAN!",
      "excerpt": "In this best-of-5 series of professional StarCraft 2 I commentate a match between soO and Dream. soO is one of the most well known names in the StarCraft scene, however I had not heard of Dream in a few a years. Turns out he likes to play greedy Terran buid orders.  This match is from Olimoleague: http://patreon.com/olimoley",
      "sourceUrl": "https://smartableai.github.io/starcraft2/api/games/lowkotv-starcraft-2-the-greedy-terran/index.json",
      "webUrl": "https://smartable.ai/apps/starcraft2/game/lowkotv-starcraft-2-the-greedy-terran/",
      "originalUrl": "https://youtube.com/watch?v=OjtpUauGITs",
      "featuredContent": "<iframe width=\"800\" height=\"500\" frameborder=\"0\" src=\"https://www.youtube.com/embed/OjtpUauGITs\" allow=\"accelerometer; autoplay; encrypted-media; gyroscope; picture-in-picture\" allowfullscreen></iframe>",
      "length": "PT42M24S",
      "provider": {
        "name": "LowkoTV",
        "domain": "lowko.tv",
        "images": [
          {
            "url": "https://smartableai.github.io/starcraft2/assets/images/organizations/lowko.tv-50x50.jpg",
            "width": 50,
            "height": 50,
            "isCached": false
          }
        ]
      },
      "topics": [
        "StarCraft 2",
        "Terran"
      ],
      "heat": 51,
      "images": [
        {
          "url": "https://i.ytimg.com/vi/OjtpUauGITs/maxresdefault.jpg",
          "width": 1280,
          "height": 720,
          "isCached": true
        }
      ],
      "content": "\r\n",
      "type": "video",
      "publishedDateTime": "2019-06-26T11:09:40-07:00"
    },
    {
      "path": "_games/lowkotv-starcraft-2-the-hero-colossus.md",
      "title": "StarCraft 2: THE HERO COLOSSUS!",
      "excerpt": "Special vs Stats in a best-of-3 of professional StarCraft 2. Subscribe for more videos: http://lowko.tv/youtube 50+ Tactical Nukes: https://youtu.be/xKYulaEILB0  A really close series of Protoss vs Terran. Solid macro, tons of Marines and Marauders, a lucky Stasis Ward and some excellent Colossus micro.",
      "sourceUrl": "https://smartableai.github.io/starcraft2/api/games/lowkotv-starcraft-2-the-hero-colossus/index.json",
      "webUrl": "https://smartable.ai/apps/starcraft2/game/lowkotv-starcraft-2-the-hero-colossus/",
      "originalUrl": "https://youtube.com/watch?v=f-G83HG-Ptg",
      "featuredContent": "<iframe width=\"800\" height=\"500\" frameborder=\"0\" src=\"https://www.youtube.com/embed/f-G83HG-Ptg\" allow=\"accelerometer; autoplay; encrypted-media; gyroscope; picture-in-picture\" allowfullscreen></iframe>",
      "length": "PT32M",
      "provider": {
        "name": "LowkoTV",
        "domain": "lowko.tv",
        "images": [
          {
            "url": "https://smartableai.github.io/starcraft2/assets/images/organizations/lowko.tv-50x50.jpg",
            "width": 50,
            "height": 50,
            "isCached": false
          }
        ]
      },
      "topics": [
        "StarCraft 2",
        "Protoss"
      ],
      "heat": 51,
      "images": [
        {
          "url": "https://i.ytimg.com/vi/f-G83HG-Ptg/maxresdefault.jpg",
          "width": 1280,
          "height": 720,
          "isCached": true
        }
      ],
      "content": "\r\n",
      "type": "video",
      "publishedDateTime": "2019-03-28T04:04:46-07:00"
    },
    {
      "path": "_games/lowkotv-starcraft-2-the-nexus-all-in.md",
      "title": "StarCraft 2: THE NEXUS ALL-IN?!",
      "excerpt": "Taking Protoss cheese to a whole new level. Subscribe for more videos: http://lowko.tv/youtube Comeback Mechanics: https://goo.gl/qqP9rB  Why play macro when you can build a Nexus inside of your opponents main base and win the game super early on anyway? Mistakes were made...  If you have an awesome",
      "sourceUrl": "https://smartableai.github.io/starcraft2/api/games/lowkotv-starcraft-2-the-nexus-all-in/index.json",
      "webUrl": "https://smartable.ai/apps/starcraft2/game/lowkotv-starcraft-2-the-nexus-all-in/",
      "originalUrl": "https://youtube.com/watch?v=Fs3Z2tzWgCw",
      "featuredContent": "<iframe width=\"800\" height=\"500\" frameborder=\"0\" src=\"https://www.youtube.com/embed/Fs3Z2tzWgCw\" allow=\"accelerometer; autoplay; encrypted-media; gyroscope; picture-in-picture\" allowfullscreen></iframe>",
      "length": "PT15M39S",
      "provider": {
        "name": "LowkoTV",
        "domain": "lowko.tv",
        "images": [
          {
            "url": "https://smartableai.github.io/starcraft2/assets/images/organizations/lowko.tv-50x50.jpg",
            "width": 50,
            "height": 50,
            "isCached": false
          }
        ]
      },
      "topics": [
        "StarCraft 2",
        "Protoss"
      ],
      "heat": 51,
      "images": [
        {
          "url": "https://i.ytimg.com/vi/Fs3Z2tzWgCw/maxresdefault.jpg",
          "width": 1280,
          "height": 720,
          "isCached": true
        }
      ],
      "content": "\r\n",
      "type": "video",
      "publishedDateTime": "2018-04-28T03:04:08-07:00"
    },
    {
      "path": "_games/lowkotv-starcraft-2-the-offensive-gg.md",
      "title": "StarCraft 2: The Offensive GG!",
      "excerpt": "An epic Diamond League match of Zerg vs Zerg. Subscribe for more videos: http://lowko.tv/youtube Trading Spawn Locations: https://goo.gl/CfmNtq  One of the players in this match of StarCraft 2 decides to cheese. No surprise there, as it is one of the most common ways of playing the matchup on the ladder.",
      "sourceUrl": "https://smartableai.github.io/starcraft2/api/games/lowkotv-starcraft-2-the-offensive-gg/index.json",
      "webUrl": "https://smartable.ai/apps/starcraft2/game/lowkotv-starcraft-2-the-offensive-gg/",
      "originalUrl": "https://youtube.com/watch?v=OB3767bULqg",
      "featuredContent": "<iframe width=\"800\" height=\"500\" frameborder=\"0\" src=\"https://www.youtube.com/embed/OB3767bULqg\" allow=\"accelerometer; autoplay; encrypted-media; gyroscope; picture-in-picture\" allowfullscreen></iframe>",
      "length": "PT16M19S",
      "provider": {
        "name": "LowkoTV",
        "domain": "lowko.tv",
        "images": [
          {
            "url": "https://smartableai.github.io/starcraft2/assets/images/organizations/lowko.tv-50x50.jpg",
            "width": 50,
            "height": 50,
            "isCached": false
          }
        ]
      },
      "topics": [
        "StarCraft 2"
      ],
      "heat": 51,
      "images": [
        {
          "url": "https://i.ytimg.com/vi/OB3767bULqg/maxresdefault.jpg",
          "width": 1280,
          "height": 720,
          "isCached": true
        }
      ],
      "content": "\r\n",
      "type": "video",
      "publishedDateTime": "2018-01-22T05:49:10-08:00"
    },
    {
      "path": "_games/lowkotv-starcraft-2-the-old-school-zerg.md",
      "title": "StarCraft 2: The OLD SCHOOL Zerg!",
      "excerpt": "A seriously cool game of Zerg vs Protoss between Leenock and Stats. Subscribe for more videos: http://lowko.tv/youtube Professionals cheesing: https://goo.gl/APqMmJ  Hydralisk Lurker into Mutalisk into Corruptors into massive amounts of counter attacks and a Spine Crawler forest. A very cool Zerg playstyle",
      "sourceUrl": "https://smartableai.github.io/starcraft2/api/games/lowkotv-starcraft-2-the-old-school-zerg/index.json",
      "webUrl": "https://smartable.ai/apps/starcraft2/game/lowkotv-starcraft-2-the-old-school-zerg/",
      "originalUrl": "https://youtube.com/watch?v=WIVPQlTxXVQ",
      "featuredContent": "<iframe width=\"800\" height=\"500\" frameborder=\"0\" src=\"https://www.youtube.com/embed/WIVPQlTxXVQ\" allow=\"accelerometer; autoplay; encrypted-media; gyroscope; picture-in-picture\" allowfullscreen></iframe>",
      "length": "PT20M1S",
      "provider": {
        "name": "LowkoTV",
        "domain": "lowko.tv",
        "images": [
          {
            "url": "https://smartableai.github.io/starcraft2/assets/images/organizations/lowko.tv-50x50.jpg",
            "width": 50,
            "height": 50,
            "isCached": false
          }
        ]
      },
      "topics": [
        "StarCraft 2",
        "Zerg"
      ],
      "heat": 51,
      "images": [
        {
          "url": "https://i.ytimg.com/vi/WIVPQlTxXVQ/maxresdefault.jpg",
          "width": 1280,
          "height": 720,
          "isCached": true
        }
      ],
      "content": "\r\n",
      "type": "video",
      "publishedDateTime": "2018-04-24T03:18:20-07:00"
    },
    {
      "path": "_games/lowkotv-starcraft-2-the-protoss-hit-squad-bo5.md",
      "title": "StarCraft 2: THE PROTOSS HIT SQUAD! (Bo5)",
      "excerpt": "An awesome best-of-5 between Elazer and Neeb. Subscribe for more videos: http://lowko.tv/youtube More StarCraft 2 casts: https://goo.gl/vx3A7i  A variety of playstyles in all of the games. However, it is noticable that Neeb is incredibly good at taking out his opponents workers. Even though he makes",
      "sourceUrl": "https://smartableai.github.io/starcraft2/api/games/lowkotv-starcraft-2-the-protoss-hit-squad-bo5/index.json",
      "webUrl": "https://smartable.ai/apps/starcraft2/game/lowkotv-starcraft-2-the-protoss-hit-squad-bo5/",
      "originalUrl": "https://youtube.com/watch?v=QYSV69RsMEg",
      "featuredContent": "<iframe width=\"800\" height=\"500\" frameborder=\"0\" src=\"https://www.youtube.com/embed/QYSV69RsMEg\" allow=\"accelerometer; autoplay; encrypted-media; gyroscope; picture-in-picture\" allowfullscreen></iframe>",
      "length": "PT1H1M4S",
      "provider": {
        "name": "LowkoTV",
        "domain": "lowko.tv",
        "images": [
          {
            "url": "https://smartableai.github.io/starcraft2/assets/images/organizations/lowko.tv-50x50.jpg",
            "width": 50,
            "height": 50,
            "isCached": false
          }
        ]
      },
      "topics": [
        "StarCraft 2",
        "Protoss"
      ],
      "heat": 51,
      "images": [
        {
          "url": "https://i.ytimg.com/vi/QYSV69RsMEg/maxresdefault.jpg",
          "width": 1280,
          "height": 720,
          "isCached": true
        }
      ],
      "content": "\r\n",
      "type": "video",
      "publishedDateTime": "2018-02-07T04:23:51-08:00"
    },
    {
      "path": "_games/lowkotv-starcraft-2-the-spine-crawler-contain.md",
      "title": "StarCraft 2: THE SPINE CRAWLER CONTAIN!",
      "excerpt": "Not quite your ordinary game of StarCraft 2... Crazy! Subscribe for more videos: http://lowko.tv/youtube The Crescent Moon Rush: https://goo.gl/jXDfvA  In this Diamond League Zerg vs Terran, the Zerg player decides to play something that his opponent did not expect... Contain him with Spine Crawlers",
      "sourceUrl": "https://smartableai.github.io/starcraft2/api/games/lowkotv-starcraft-2-the-spine-crawler-contain/index.json",
      "webUrl": "https://smartable.ai/apps/starcraft2/game/lowkotv-starcraft-2-the-spine-crawler-contain/",
      "originalUrl": "https://youtube.com/watch?v=W4Fj5ga9fe8",
      "featuredContent": "<iframe width=\"800\" height=\"500\" frameborder=\"0\" src=\"https://www.youtube.com/embed/W4Fj5ga9fe8\" allow=\"accelerometer; autoplay; encrypted-media; gyroscope; picture-in-picture\" allowfullscreen></iframe>",
      "length": "PT15M36S",
      "provider": {
        "name": "LowkoTV",
        "domain": "lowko.tv",
        "images": [
          {
            "url": "https://smartableai.github.io/starcraft2/assets/images/organizations/lowko.tv-50x50.jpg",
            "width": 50,
            "height": 50,
            "isCached": false
          }
        ]
      },
      "topics": [
        "StarCraft 2"
      ],
      "heat": 51,
      "images": [
        {
          "url": "https://i.ytimg.com/vi/W4Fj5ga9fe8/maxresdefault.jpg",
          "width": 1280,
          "height": 720,
          "isCached": true
        }
      ],
      "content": "\r\n",
      "type": "video",
      "publishedDateTime": "2018-09-07T02:39:31-07:00"
    },
    {
      "path": "_games/lowkotv-starcraft-2-the-tactical-sensor-tower.md",
      "title": "StarCraft 2: The TACTICAL Sensor Tower!",
      "excerpt": "Easily one of the silliest games I've seen recently. Subscribe for more videos: http://lowko.tv/youtube The Command Center Bully: https://goo.gl/yBfzFD  With a rather unusual early game strategy, in this Zerg versus Terran we see both players making several hilarious mistakes make the game flip back",
      "sourceUrl": "https://smartableai.github.io/starcraft2/api/games/lowkotv-starcraft-2-the-tactical-sensor-tower/index.json",
      "webUrl": "https://smartable.ai/apps/starcraft2/game/lowkotv-starcraft-2-the-tactical-sensor-tower/",
      "originalUrl": "https://youtube.com/watch?v=f4uIRBAQtTs",
      "featuredContent": "<iframe width=\"800\" height=\"500\" frameborder=\"0\" src=\"https://www.youtube.com/embed/f4uIRBAQtTs\" allow=\"accelerometer; autoplay; encrypted-media; gyroscope; picture-in-picture\" allowfullscreen></iframe>",
      "length": "PT24M14S",
      "provider": {
        "name": "LowkoTV",
        "domain": "lowko.tv",
        "images": [
          {
            "url": "https://smartableai.github.io/starcraft2/assets/images/organizations/lowko.tv-50x50.jpg",
            "width": 50,
            "height": 50,
            "isCached": false
          }
        ]
      },
      "topics": [
        "StarCraft 2"
      ],
      "heat": 51,
      "images": [
        {
          "url": "https://i.ytimg.com/vi/f4uIRBAQtTs/maxresdefault.jpg",
          "width": 1280,
          "height": 720,
          "isCached": true
        }
      ],
      "content": "\r\n",
      "type": "video",
      "publishedDateTime": "2017-10-28T09:55:31-07:00"
    },
    {
      "path": "_games/lowkotv-starcraft-2-the-tempest-all-in.md",
      "title": "StarCraft 2: THE TEMPEST ALL-IN!",
      "excerpt": "Bly vs Harstem in a macro match of Zerg vs Protoss in StarCraft 2. Subscribe for more videos: http://lowko.tv/youtube More epic StarCraft 2: https://goo.gl/HFczUz  In this match we start off with a bang in the form of a very annoying Drone, becoming a proxy Hatchery inside of the Protoss natural expansion.",
      "sourceUrl": "https://smartableai.github.io/starcraft2/api/games/lowkotv-starcraft-2-the-tempest-all-in/index.json",
      "webUrl": "https://smartable.ai/apps/starcraft2/game/lowkotv-starcraft-2-the-tempest-all-in/",
      "originalUrl": "https://youtube.com/watch?v=OfCp0idQCfg",
      "featuredContent": "<iframe width=\"800\" height=\"500\" frameborder=\"0\" src=\"https://www.youtube.com/embed/OfCp0idQCfg\" allow=\"accelerometer; autoplay; encrypted-media; gyroscope; picture-in-picture\" allowfullscreen></iframe>",
      "length": "PT21M43S",
      "provider": {
        "name": "LowkoTV",
        "domain": "lowko.tv",
        "images": [
          {
            "url": "https://smartableai.github.io/starcraft2/assets/images/organizations/lowko.tv-50x50.jpg",
            "width": 50,
            "height": 50,
            "isCached": false
          }
        ]
      },
      "topics": [
        "StarCraft 2"
      ],
      "heat": 51,
      "images": [
        {
          "url": "https://i.ytimg.com/vi/OfCp0idQCfg/maxresdefault.jpg",
          "width": 1280,
          "height": 720,
          "isCached": true
        }
      ],
      "content": "\r\n",
      "type": "video",
      "publishedDateTime": "2018-12-15T03:48:43-08:00"
    },
    {
      "path": "_games/lowkotv-starcraft-2-the-tempo-advantage.md",
      "title": "StarCraft 2: The Tempo Advantage!",
      "excerpt": "Massive Widow Mine hits in this professional match in StarCraft 2 of Zerg versus Terran between Cure and Impact.  Get more videos & support my work: http://www.patreon.com/lowkotv  Be part of the community on Discord: http://discord.gg/lowkotv The hardware setup I use: https://lowko.tv/setup/  This game",
      "sourceUrl": "https://smartableai.github.io/starcraft2/api/games/lowkotv-starcraft-2-the-tempo-advantage/index.json",
      "webUrl": "https://smartable.ai/apps/starcraft2/game/lowkotv-starcraft-2-the-tempo-advantage/",
      "originalUrl": "https://youtube.com/watch?v=0EQmbSNMKJ0",
      "featuredContent": "<iframe width=\"800\" height=\"500\" frameborder=\"0\" src=\"https://www.youtube.com/embed/0EQmbSNMKJ0\" allow=\"accelerometer; autoplay; encrypted-media; gyroscope; picture-in-picture\" allowfullscreen></iframe>",
      "length": "PT19M55S",
      "provider": {
        "name": "LowkoTV",
        "domain": "lowko.tv",
        "images": [
          {
            "url": "https://smartableai.github.io/starcraft2/assets/images/organizations/lowko.tv-50x50.jpg",
            "width": 50,
            "height": 50,
            "isCached": false
          }
        ]
      },
      "topics": [
        "StarCraft 2"
      ],
      "heat": 51,
      "images": [
        {
          "url": "https://i.ytimg.com/vi/0EQmbSNMKJ0/maxresdefault.jpg",
          "width": 1280,
          "height": 720,
          "isCached": true
        }
      ],
      "content": "\r\n",
      "type": "video",
      "publishedDateTime": "2019-09-04T03:07:37-07:00"
    },
    {
      "path": "_games/lowkotv-starcraft-2-the-ultralisk-bait.md",
      "title": "StarCraft 2: The Ultralisk Bait!",
      "excerpt": "Professional match of StarCraft 2 between Impact and Cure, a Zerg versus Terran with shiny new Ultralisk skins and a very high tempo based playstyle.  Get more videos & support my work: http://www.patreon.com/lowkotv  My second channel: http://lowko.tv/morelowko Lowko Merch: http://lowko.tv/merch  Be",
      "sourceUrl": "https://smartableai.github.io/starcraft2/api/games/lowkotv-starcraft-2-the-ultralisk-bait/index.json",
      "webUrl": "https://smartable.ai/apps/starcraft2/game/lowkotv-starcraft-2-the-ultralisk-bait/",
      "originalUrl": "https://youtube.com/watch?v=PYshl_a0ON4",
      "featuredContent": "<iframe width=\"800\" height=\"500\" frameborder=\"0\" src=\"https://www.youtube.com/embed/PYshl_a0ON4\" allow=\"accelerometer; autoplay; encrypted-media; gyroscope; picture-in-picture\" allowfullscreen></iframe>",
      "length": "PT17M37S",
      "provider": {
        "name": "LowkoTV",
        "domain": "lowko.tv",
        "images": [
          {
            "url": "https://smartableai.github.io/starcraft2/assets/images/organizations/lowko.tv-50x50.jpg",
            "width": 50,
            "height": 50,
            "isCached": false
          }
        ]
      },
      "topics": [
        "StarCraft 2"
      ],
      "heat": 51,
      "images": [
        {
          "url": "https://i.ytimg.com/vi/PYshl_a0ON4/maxresdefault.jpg",
          "width": 1280,
          "height": 720,
          "isCached": true
        }
      ],
      "content": "\r\n",
      "type": "video",
      "publishedDateTime": "2019-10-09T03:17:11-07:00"
    },
    {
      "path": "_games/lowkotv-starcraft-2-thor-drop-shenanigans.md",
      "title": "StarCraft 2: THOR DROP Shenanigans!",
      "excerpt": "It is time for a best-of-3 series of professional StarCraft 2! Subscribe for more videos: http://lowko.tv/youtube The Banshee Hit Squad: https://goo.gl/dRti8W  Gumiho versus Solar. A very evenly matched game of StarCraft 2. In this best-of-3 we see Mech from the Terran player in all three games. However,",
      "sourceUrl": "https://smartableai.github.io/starcraft2/api/games/lowkotv-starcraft-2-thor-drop-shenanigans/index.json",
      "webUrl": "https://smartable.ai/apps/starcraft2/game/lowkotv-starcraft-2-thor-drop-shenanigans/",
      "originalUrl": "https://youtube.com/watch?v=HpVX95VSrb4",
      "featuredContent": "<iframe width=\"800\" height=\"500\" frameborder=\"0\" src=\"https://www.youtube.com/embed/HpVX95VSrb4\" allow=\"accelerometer; autoplay; encrypted-media; gyroscope; picture-in-picture\" allowfullscreen></iframe>",
      "length": "PT44M50S",
      "provider": {
        "name": "LowkoTV",
        "domain": "lowko.tv",
        "images": [
          {
            "url": "https://smartableai.github.io/starcraft2/assets/images/organizations/lowko.tv-50x50.jpg",
            "width": 50,
            "height": 50,
            "isCached": false
          }
        ]
      },
      "topics": [
        "StarCraft 2"
      ],
      "heat": 51,
      "images": [
        {
          "url": "https://i.ytimg.com/vi/HpVX95VSrb4/maxresdefault.jpg",
          "width": 1280,
          "height": 720,
          "isCached": true
        }
      ],
      "content": "\r\n",
      "type": "video",
      "publishedDateTime": "2018-04-06T04:56:57-07:00"
    },
    {
      "path": "_games/lowkotv-starcraft-2-thor-drops.md",
      "title": "StarCraft 2: THOR DROPS?!",
      "excerpt": "Fear the thunder! Rogue vs Gumiho in StarCraft 2. Subscribe for more videos: http://lowko.tv/youtube Intense Zerg vs Protoss: https://goo.gl/D6Qj6z  Terran Mech has been going through quite a few changes lately. Gumiho has figured out a way to make it viable against Zerg where it was considered to be",
      "sourceUrl": "https://smartableai.github.io/starcraft2/api/games/lowkotv-starcraft-2-thor-drops/index.json",
      "webUrl": "https://smartable.ai/apps/starcraft2/game/lowkotv-starcraft-2-thor-drops/",
      "originalUrl": "https://youtube.com/watch?v=isEYLoAKyWE",
      "featuredContent": "<iframe width=\"800\" height=\"500\" frameborder=\"0\" src=\"https://www.youtube.com/embed/isEYLoAKyWE\" allow=\"accelerometer; autoplay; encrypted-media; gyroscope; picture-in-picture\" allowfullscreen></iframe>",
      "length": "PT28M44S",
      "provider": {
        "name": "LowkoTV",
        "domain": "lowko.tv",
        "images": [
          {
            "url": "https://smartableai.github.io/starcraft2/assets/images/organizations/lowko.tv-50x50.jpg",
            "width": 50,
            "height": 50,
            "isCached": false
          }
        ]
      },
      "topics": [
        "StarCraft 2"
      ],
      "heat": 51,
      "images": [
        {
          "url": "https://i.ytimg.com/vi/isEYLoAKyWE/maxresdefault.jpg",
          "width": 1280,
          "height": 720,
          "isCached": true
        }
      ],
      "content": "\r\n",
      "type": "video",
      "publishedDateTime": "2017-08-09T02:55:00-07:00"
    },
    {
      "path": "_games/lowkotv-starcraft-2-thor-vs-thor-battles.md",
      "title": "StarCraft 2: THOR vs THOR BATTLES!",
      "excerpt": "An early gentleman's agreement to make Thors only in TvT! Subscribe for more videos: http://lowko.tv/youtube The Crescent Moon rush: https://goo.gl/FUtDgG  A fun Gold League match of Terran vs Terran with lots of Thors. While Terran has a lot of great units, mass Thor is not something that we see every",
      "sourceUrl": "https://smartableai.github.io/starcraft2/api/games/lowkotv-starcraft-2-thor-vs-thor-battles/index.json",
      "webUrl": "https://smartable.ai/apps/starcraft2/game/lowkotv-starcraft-2-thor-vs-thor-battles/",
      "originalUrl": "https://youtube.com/watch?v=AWbPok7lFNA",
      "featuredContent": "<iframe width=\"800\" height=\"500\" frameborder=\"0\" src=\"https://www.youtube.com/embed/AWbPok7lFNA\" allow=\"accelerometer; autoplay; encrypted-media; gyroscope; picture-in-picture\" allowfullscreen></iframe>",
      "length": "PT17M19S",
      "provider": {
        "name": "LowkoTV",
        "domain": "lowko.tv",
        "images": [
          {
            "url": "https://smartableai.github.io/starcraft2/assets/images/organizations/lowko.tv-50x50.jpg",
            "width": 50,
            "height": 50,
            "isCached": false
          }
        ]
      },
      "topics": [
        "StarCraft 2"
      ],
      "heat": 51,
      "images": [
        {
          "url": "https://i.ytimg.com/vi/AWbPok7lFNA/maxresdefault.jpg",
          "width": 1280,
          "height": 720,
          "isCached": true
        }
      ],
      "content": "\r\n",
      "type": "video",
      "publishedDateTime": "2018-12-12T02:29:56-08:00"
    },
    {
      "path": "_games/lowkotv-starcraft-2-thors-vs-disruptors-innovation-vs-parting.md",
      "title": "StarCraft 2: THORS vs DISRUPTORS? (INnoVation vs PartinG)",
      "excerpt": "Awesome game of top-level StarCraft 2 between INnoVation and PartinG. In this game of top level Terran versus Protoss both players have to constantly micro to get the most out of their StarCraft 2 units.  Get more videos & support my work: http://www.patreon.com/lowkotv  My second channel: http://lowko.tv/morelowko",
      "sourceUrl": "https://smartableai.github.io/starcraft2/api/games/lowkotv-starcraft-2-thors-vs-disruptors-innovation-vs-parting/index.json",
      "webUrl": "https://smartable.ai/apps/starcraft2/game/lowkotv-starcraft-2-thors-vs-disruptors-innovation-vs-parting/",
      "originalUrl": "https://youtube.com/watch?v=oR6SwL0SIxU",
      "featuredContent": "<iframe width=\"800\" height=\"500\" frameborder=\"0\" src=\"https://www.youtube.com/embed/oR6SwL0SIxU\" allow=\"accelerometer; autoplay; encrypted-media; gyroscope; picture-in-picture\" allowfullscreen></iframe>",
      "length": "PT23M48S",
      "provider": {
        "name": "LowkoTV",
        "domain": "lowko.tv",
        "images": [
          {
            "url": "https://smartableai.github.io/starcraft2/assets/images/organizations/lowko.tv-50x50.jpg",
            "width": 50,
            "height": 50,
            "isCached": false
          }
        ]
      },
      "topics": [
        "StarCraft 2",
        "Terran",
        "Protoss"
      ],
      "heat": 51,
      "images": [
        {
          "url": "https://i.ytimg.com/vi/oR6SwL0SIxU/maxresdefault.jpg",
          "width": 1280,
          "height": 720,
          "isCached": true
        }
      ],
      "content": "\r\n",
      "type": "video",
      "publishedDateTime": "2020-08-11T03:23:26-07:00"
    },
    {
      "path": "_games/lowkotv-starcraft-2-tons-of-tanks-neeblet-vs-uthermal.md",
      "title": "StarCraft 2: TONS OF TANKS! (Neeblet vs uThermal)",
      "excerpt": "Protoss versus Terran has changed... A lot. Subscribe for more videos: http://lowko.tv/youtube More StarCraft 2 Commentary: https://goo.gl/xhqtzW  In this match between uThermal and Neeblet we see some of the major changes to the PvT matchup come into play. Since the Disruptor got nerfed, their counter",
      "sourceUrl": "https://smartableai.github.io/starcraft2/api/games/lowkotv-starcraft-2-tons-of-tanks-neeblet-vs-uthermal/index.json",
      "webUrl": "https://smartable.ai/apps/starcraft2/game/lowkotv-starcraft-2-tons-of-tanks-neeblet-vs-uthermal/",
      "originalUrl": "https://youtube.com/watch?v=nphhaf8WfoM",
      "featuredContent": "<iframe width=\"800\" height=\"500\" frameborder=\"0\" src=\"https://www.youtube.com/embed/nphhaf8WfoM\" allow=\"accelerometer; autoplay; encrypted-media; gyroscope; picture-in-picture\" allowfullscreen></iframe>",
      "length": "PT24M53S",
      "provider": {
        "name": "LowkoTV",
        "domain": "lowko.tv",
        "images": [
          {
            "url": "https://smartableai.github.io/starcraft2/assets/images/organizations/lowko.tv-50x50.jpg",
            "width": 50,
            "height": 50,
            "isCached": false
          }
        ]
      },
      "topics": [
        "StarCraft 2",
        "Terran"
      ],
      "heat": 51,
      "images": [
        {
          "url": "https://i.ytimg.com/vi/nphhaf8WfoM/maxresdefault.jpg",
          "width": 1280,
          "height": 720,
          "isCached": true
        }
      ],
      "content": "\r\n",
      "type": "video",
      "publishedDateTime": "2017-11-16T23:35:27-08:00"
    },
    {
      "path": "_games/lowkotv-starcraft-2-top-level-master-class.md",
      "title": "StarCraft 2: TOP-LEVEL MASTER CLASS!",
      "excerpt": "Serral vs INnoVation in an epic match of Zerg vs Terran. Subscribe for more videos: http://lowko.tv/youtube Insane Protoss macro: https://goo.gl/kYVEow  What a game! INnoVation really shows how to play late game versus an extremely cautious Zerg players. However, Serral is ready to spring the trap. In",
      "sourceUrl": "https://smartableai.github.io/starcraft2/api/games/lowkotv-starcraft-2-top-level-master-class/index.json",
      "webUrl": "https://smartable.ai/apps/starcraft2/game/lowkotv-starcraft-2-top-level-master-class/",
      "originalUrl": "https://youtube.com/watch?v=FzjCKHA3Zc0",
      "featuredContent": "<iframe width=\"800\" height=\"500\" frameborder=\"0\" src=\"https://www.youtube.com/embed/FzjCKHA3Zc0\" allow=\"accelerometer; autoplay; encrypted-media; gyroscope; picture-in-picture\" allowfullscreen></iframe>",
      "length": "PT44M24S",
      "provider": {
        "name": "LowkoTV",
        "domain": "lowko.tv",
        "images": [
          {
            "url": "https://smartableai.github.io/starcraft2/assets/images/organizations/lowko.tv-50x50.jpg",
            "width": 50,
            "height": 50,
            "isCached": false
          }
        ]
      },
      "topics": [
        "StarCraft 2"
      ],
      "heat": 51,
      "images": [
        {
          "url": "https://i.ytimg.com/vi/FzjCKHA3Zc0/maxresdefault.jpg",
          "width": 1280,
          "height": 720,
          "isCached": true
        }
      ],
      "content": "\r\n",
      "type": "video",
      "publishedDateTime": "2019-03-04T05:24:19-08:00"
    },
    {
      "path": "_games/lowkotv-starcraft-2-top-of-the-line-protoss-vs-terran.md",
      "title": "StarCraft 2: TOP-OF-THE-LINE Protoss vs Terran!",
      "excerpt": "A solid best-of-5 series between INnoVation and herO. Subscribe for more videos: http://lowko.tv/youtube Intense Zerg vs Protoss: https://goo.gl/D6Qj6z  In this series there is a clash between two titans. Both players are the statistical rank 1 for their respective races. herO is known as the best Protoss",
      "sourceUrl": "https://smartableai.github.io/starcraft2/api/games/lowkotv-starcraft-2-top-of-the-line-protoss-vs-terran/index.json",
      "webUrl": "https://smartable.ai/apps/starcraft2/game/lowkotv-starcraft-2-top-of-the-line-protoss-vs-terran/",
      "originalUrl": "https://youtube.com/watch?v=9DpFrmdyarU",
      "featuredContent": "<iframe width=\"800\" height=\"500\" frameborder=\"0\" src=\"https://www.youtube.com/embed/9DpFrmdyarU\" allow=\"accelerometer; autoplay; encrypted-media; gyroscope; picture-in-picture\" allowfullscreen></iframe>",
      "length": "PT47M15S",
      "provider": {
        "name": "LowkoTV",
        "domain": "lowko.tv",
        "images": [
          {
            "url": "https://smartableai.github.io/starcraft2/assets/images/organizations/lowko.tv-50x50.jpg",
            "width": 50,
            "height": 50,
            "isCached": false
          }
        ]
      },
      "topics": [
        "StarCraft 2",
        "Terran",
        "Protoss"
      ],
      "heat": 51,
      "images": [
        {
          "url": "https://i.ytimg.com/vi/9DpFrmdyarU/maxresdefault.jpg",
          "width": 1280,
          "height": 720,
          "isCached": true
        }
      ],
      "content": "\r\n",
      "type": "video",
      "publishedDateTime": "2017-08-05T05:10:07-07:00"
    },
    {
      "path": "_games/lowkotv-starcraft-2-ultimate-protoss-efficiency.md",
      "title": "StarCraft 2: ULTIMATE Protoss Efficiency!",
      "excerpt": "An epic game of Zerg vs Protoss between Neeb and Rogue. Subscribe for more videos: http://lowko.tv/youtube Crazy Protoss micro: https://goo.gl/tvhEza  Rogue decides to not play the typical Zerg late game, but instead swarms his opponent with constant waves of Zerg attacks. Neeb however, decides to sit",
      "sourceUrl": "https://smartableai.github.io/starcraft2/api/games/lowkotv-starcraft-2-ultimate-protoss-efficiency/index.json",
      "webUrl": "https://smartable.ai/apps/starcraft2/game/lowkotv-starcraft-2-ultimate-protoss-efficiency/",
      "originalUrl": "https://youtube.com/watch?v=nZjZSAa4j50",
      "featuredContent": "<iframe width=\"800\" height=\"500\" frameborder=\"0\" src=\"https://www.youtube.com/embed/nZjZSAa4j50\" allow=\"accelerometer; autoplay; encrypted-media; gyroscope; picture-in-picture\" allowfullscreen></iframe>",
      "length": "PT22M27S",
      "provider": {
        "name": "LowkoTV",
        "domain": "lowko.tv",
        "images": [
          {
            "url": "https://smartableai.github.io/starcraft2/assets/images/organizations/lowko.tv-50x50.jpg",
            "width": 50,
            "height": 50,
            "isCached": false
          }
        ]
      },
      "topics": [
        "StarCraft 2",
        "Protoss"
      ],
      "heat": 51,
      "images": [
        {
          "url": "https://i.ytimg.com/vi/nZjZSAa4j50/maxresdefault.jpg",
          "width": 1280,
          "height": 720,
          "isCached": true
        }
      ],
      "content": "\r\n",
      "type": "video",
      "publishedDateTime": "2018-05-21T01:58:00-07:00"
    }
  ],
  "nextPage": 17
}